{
    "date": {
        "session_day": "101st day", 
        "date_iso": "2012-04-05T00:00:00", 
        "date_string": "THURSDAY, APRIL 5, 2012"
    }, 
    "role_call": [
        "Bakk", 
        "Benson", 
        "Bonoff", 
        "Brown", 
        "Carlson", 
        "Chamberlain", 
        "Cohen", 
        "Dahms", 
        "Daley", 
        "DeKruif", 
        "Dziedzic", 
        "Eaton", 
        "Fischbach", 
        "Gazelka", 
        "Gerlach", 
        "Gimse", 
        "Goodwin", 
        "Hall", 
        "Hann", 
        "Harrington", 
        "Hayden", 
        "Higgins", 
        "Hoffman", 
        "Howe", 
        "Ingebrigtsen", 
        "Jungbauer", 
        "Kelash", 
        "Koch", 
        "Kruse", 
        "Latz", 
        "Lillie", 
        "Limmer", 
        "Lourey", 
        "Magnus", 
        "Marty", 
        "McGuire", 
        "Metzen", 
        "Miller", 
        "Nelson", 
        "Newman", 
        "Nienow", 
        "Olson", 
        "Ortman", 
        "Pappas", 
        "Parry", 
        "Pederson", 
        "Reinert", 
        "Rest", 
        "Robling", 
        "Rosen", 
        "Saxhaug", 
        "Senjem", 
        "Sheran", 
        "Sieben", 
        "Skoe", 
        "Sparks", 
        "Stumpf", 
        "Thompson", 
        "Tomassoni", 
        "Torres Ray", 
        "Vandeveer", 
        "Wiger", 
        "Wolf"
    ], 
    "bill_votes": [
        {
            "title": "S.F. No. 1586", 
            "pass": true, 
            "status_string": " amended by the Conference Committee, was repassed and its title was agreed to", 
            "amended": false, 
            "yays": 58, 
            "nays": 0, 
            "affirmatives": [
                "Bakk", 
                "Benson", 
                "Bonoff", 
                "Brown", 
                "Carlson", 
                "Chamberlain", 
                "Cohen", 
                "Dahms", 
                "Dziedzic", 
                "Eaton", 
                "Fischbach", 
                "Gazelka", 
                "Gerlach", 
                "Gimse", 
                "Goodwin", 
                "Hall", 
                "Hann", 
                "Harrington", 
                "Higgins", 
                "Hoffman", 
                "Howe", 
                "Ingebrigtsen", 
                "Jungbauer", 
                "Kelash", 
                "Koch", 
                "Kruse", 
                "Latz", 
                "Lillie", 
                "Limmer", 
                "Lourey", 
                "Magnus", 
                "Marty", 
                "Metzen", 
                "Miller", 
                "Nelson", 
                "Newman", 
                "Nienow", 
                "Olson", 
                "Ortman", 
                "Pappas", 
                "Parry", 
                "Pederson", 
                "Rest", 
                "Robling", 
                "Rosen", 
                "Saxhaug", 
                "Senjem", 
                "Sheran", 
                "Sieben", 
                "Skoe", 
                "Sparks", 
                "Stumpf", 
                "Thompson", 
                "Tomassoni", 
                "Torres Ray", 
                "Vandeveer", 
                "Wiger", 
                "Wolf"
            ], 
            "negatives": []
        }, 
        {
            "title": "H.F. No. 1829", 
            "pass": true, 
            "status_string": "passed and its title was agreed to", 
            "amended": false, 
            "yays": 53, 
            "nays": 10, 
            "affirmatives": [
                "Bakk", 
                "Benson", 
                "Bonoff", 
                "Brown", 
                "Carlson", 
                "Chamberlain", 
                "Dahms", 
                "Daley", 
                "DeKruif", 
                "Fischbach", 
                "Gazelka", 
                "Gerlach", 
                "Gimse", 
                "Goodwin", 
                "Hall", 
                "Hann", 
                "Harrington", 
                "Hoffman", 
                "Howe", 
                "Ingebrigtsen", 
                "Jungbauer", 
                "Koch", 
                "Kruse", 
                "Latz", 
                "Lillie", 
                "Limmer", 
                "Lourey", 
                "Magnus", 
                "Metzen", 
                "Miller", 
                "Nelson", 
                "Newman", 
                "Nienow", 
                "Olson", 
                "Ortman", 
                "Parry", 
                "Pederson", 
                "Reinert", 
                "Rest", 
                "Robling", 
                "Rosen", 
                "Saxhaug", 
                "Senjem", 
                "Sheran", 
                "Sieben", 
                "Skoe", 
                "Sparks", 
                "Stumpf", 
                "Thompson", 
                "Tomassoni", 
                "Vandeveer", 
                "Wiger", 
                "Wolf"
            ], 
            "negatives": [
                "Cohen", 
                "Dziedzic", 
                "Eaton", 
                "Hayden", 
                "Higgins", 
                "Kelash", 
                "Marty", 
                "McGuire", 
                "Pappas", 
                "Torres Ray"
            ]
        }, 
        {
            "title": "S.F. No. 2121", 
            "pass": true, 
            "status_string": "passed and its title was agreed to", 
            "amended": false, 
            "yays": 62, 
            "nays": 0, 
            "affirmatives": [
                "Bakk", 
                "Benson", 
                "Bonoff", 
                "Brown", 
                "Carlson", 
                "Chamberlain", 
                "Cohen", 
                "Dahms", 
                "Daley", 
                "DeKruif", 
                "Dziedzic", 
                "Eaton", 
                "Fischbach", 
                "Gazelka", 
                "Gerlach", 
                "Gimse", 
                "Goodwin", 
                "Hall", 
                "Hann", 
                "Harrington", 
                "Hayden", 
                "Higgins", 
                "Hoffman", 
                "Howe", 
                "Ingebrigtsen", 
                "Jungbauer", 
                "Kelash", 
                "Koch", 
                "Kruse", 
                "Latz", 
                "Lillie", 
                "Limmer", 
                "Lourey", 
                "Marty", 
                "McGuire", 
                "Metzen", 
                "Miller", 
                "Nelson", 
                "Newman", 
                "Nienow", 
                "Olson", 
                "Ortman", 
                "Pappas", 
                "Parry", 
                "Pederson", 
                "Reinert", 
                "Rest", 
                "Robling", 
                "Rosen", 
                "Saxhaug", 
                "Senjem", 
                "Sheran", 
                "Sieben", 
                "Skoe", 
                "Sparks", 
                "Stumpf", 
                "Thompson", 
                "Tomassoni", 
                "Torres Ray", 
                "Vandeveer", 
                "Wiger", 
                "Wolf"
            ], 
            "negatives": []
        }, 
        {
            "title": "S.F. No. 1416", 
            "pass": true, 
            "status_string": "passed and its title was agreed to", 
            "amended": false, 
            "yays": 61, 
            "nays": 0, 
            "affirmatives": [
                "Bakk", 
                "Benson", 
                "Bonoff", 
                "Brown", 
                "Carlson", 
                "Chamberlain", 
                "Dahms", 
                "Daley", 
                "DeKruif", 
                "Dziedzic", 
                "Eaton", 
                "Fischbach", 
                "Gazelka", 
                "Gerlach", 
                "Gimse", 
                "Goodwin", 
                "Hall", 
                "Hann", 
                "Harrington", 
                "Hayden", 
                "Higgins", 
                "Hoffman", 
                "Howe", 
                "Ingebrigtsen", 
                "Jungbauer", 
                "Kelash", 
                "Koch", 
                "Kruse", 
                "Latz", 
                "Lillie", 
                "Limmer", 
                "Lourey", 
                "Marty", 
                "McGuire", 
                "Metzen", 
                "Miller", 
                "Nelson", 
                "Newman", 
                "Nienow", 
                "Olson", 
                "Ortman", 
                "Pappas", 
                "Parry", 
                "Pederson", 
                "Reinert", 
                "Rest", 
                "Robling", 
                "Rosen", 
                "Saxhaug", 
                "Senjem", 
                "Sheran", 
                "Sieben", 
                "Skoe", 
                "Sparks", 
                "Stumpf", 
                "Thompson", 
                "Tomassoni", 
                "Torres Ray", 
                "Vandeveer", 
                "Wiger", 
                "Wolf"
            ], 
            "negatives": []
        }, 
        {
            "title": "H.F. No. 2216", 
            "pass": true, 
            "status_string": "passed and its title was agreed to", 
            "amended": false, 
            "yays": 61, 
            "nays": 0, 
            "affirmatives": [
                "Bakk", 
                "Benson", 
                "Bonoff", 
                "Brown", 
                "Carlson", 
                "Chamberlain", 
                "Cohen", 
                "Dahms", 
                "Daley", 
                "DeKruif", 
                "Dziedzic", 
                "Eaton", 
                "Fischbach", 
                "Gazelka", 
                "Gerlach", 
                "Gimse", 
                "Hall", 
                "Hann", 
                "Harrington", 
                "Hayden", 
                "Higgins", 
                "Hoffman", 
                "Howe", 
                "Ingebrigtsen", 
                "Jungbauer", 
                "Kelash", 
                "Koch", 
                "Kruse", 
                "Latz", 
                "Lillie", 
                "Limmer", 
                "Lourey", 
                "Marty", 
                "McGuire", 
                "Metzen", 
                "Miller", 
                "Nelson", 
                "Newman", 
                "Nienow", 
                "Olson", 
                "Ortman", 
                "Pappas", 
                "Parry", 
                "Pederson", 
                "Reinert", 
                "Rest", 
                "Robling", 
                "Rosen", 
                "Saxhaug", 
                "Senjem", 
                "Sheran", 
                "Sieben", 
                "Skoe", 
                "Sparks", 
                "Stumpf", 
                "Thompson", 
                "Tomassoni", 
                "Torres Ray", 
                "Vandeveer", 
                "Wiger", 
                "Wolf"
            ], 
            "negatives": []
        }, 
        {
            "title": "H.F. No. 2132", 
            "pass": true, 
            "status_string": " amended, was passed and its title was agreed to", 
            "amended": false, 
            "yays": 60, 
            "nays": 1, 
            "affirmatives": [
                "Bakk", 
                "Benson", 
                "Bonoff", 
                "Brown", 
                "Carlson", 
                "Chamberlain", 
                "Cohen", 
                "Dahms", 
                "Daley", 
                "DeKruif", 
                "Dziedzic", 
                "Eaton", 
                "Fischbach", 
                "Gazelka", 
                "Gerlach", 
                "Gimse", 
                "Hall", 
                "Hann", 
                "Harrington", 
                "Hayden", 
                "Higgins", 
                "Hoffman", 
                "Howe", 
                "Ingebrigtsen", 
                "Kelash", 
                "Koch", 
                "Kruse", 
                "Latz", 
                "Lillie", 
                "Limmer", 
                "Lourey", 
                "Marty", 
                "McGuire", 
                "Metzen", 
                "Miller", 
                "Nelson", 
                "Newman", 
                "Nienow", 
                "Olson", 
                "Ortman", 
                "Pappas", 
                "Parry", 
                "Pederson", 
                "Reinert", 
                "Rest", 
                "Robling", 
                "Rosen", 
                "Saxhaug", 
                "Senjem", 
                "Sheran", 
                "Sieben", 
                "Skoe", 
                "Sparks", 
                "Stumpf", 
                "Thompson", 
                "Tomassoni", 
                "Torres Ray", 
                "Vandeveer", 
                "Wiger", 
                "Wolf"
            ], 
            "negatives": [
                "Jungbauer"
            ]
        }, 
        {
            "title": "S.F. No. 2324", 
            "pass": true, 
            "status_string": "passed and its title was agreed to", 
            "amended": false, 
            "yays": 53, 
            "nays": 8, 
            "affirmatives": [
                "Bakk", 
                "Benson", 
                "Bonoff", 
                "Carlson", 
                "Chamberlain", 
                "Cohen", 
                "Dahms", 
                "Daley", 
                "DeKruif", 
                "Dziedzic", 
                "Eaton", 
                "Fischbach", 
                "Gazelka", 
                "Gerlach", 
                "Gimse", 
                "Hann", 
                "Harrington", 
                "Hayden", 
                "Higgins", 
                "Howe", 
                "Ingebrigtsen", 
                "Jungbauer", 
                "Kelash", 
                "Koch", 
                "Kruse", 
                "Latz", 
                "Lourey", 
                "Marty", 
                "McGuire", 
                "Metzen", 
                "Miller", 
                "Nelson", 
                "Nienow", 
                "Olson", 
                "Pappas", 
                "Parry", 
                "Pederson", 
                "Reinert", 
                "Rest", 
                "Robling", 
                "Rosen", 
                "Saxhaug", 
                "Senjem", 
                "Sheran", 
                "Sieben", 
                "Skoe", 
                "Sparks", 
                "Stumpf", 
                "Tomassoni", 
                "Torres Ray", 
                "Vandeveer", 
                "Wiger", 
                "Wolf"
            ], 
            "negatives": [
                "Brown", 
                "Hall", 
                "Hoffman", 
                "Lillie", 
                "Limmer", 
                "Newman", 
                "Ortman", 
                "Thompson"
            ]
        }, 
        {
            "title": "H.F. No. 2949", 
            "pass": true, 
            "status_string": " amended, was passed and its title was agreed to", 
            "amended": false, 
            "yays": 49, 
            "nays": 13, 
            "affirmatives": [
                "Bakk", 
                "Benson", 
                "Bonoff", 
                "Brown", 
                "Carlson", 
                "Chamberlain", 
                "Dahms", 
                "Daley", 
                "DeKruif", 
                "Dziedzic", 
                "Fischbach", 
                "Gazelka", 
                "Gerlach", 
                "Gimse", 
                "Hall", 
                "Hann", 
                "Harrington", 
                "Hayden", 
                "Higgins", 
                "Hoffman", 
                "Howe", 
                "Ingebrigtsen", 
                "Jungbauer", 
                "Kelash", 
                "Koch", 
                "Kruse", 
                "Latz", 
                "Lillie", 
                "Limmer", 
                "Metzen", 
                "Miller", 
                "Nelson", 
                "Newman", 
                "Nienow", 
                "Olson", 
                "Pappas", 
                "Parry", 
                "Pederson", 
                "Robling", 
                "Rosen", 
                "Saxhaug", 
                "Senjem", 
                "Sparks", 
                "Stumpf", 
                "Thompson", 
                "Torres Ray", 
                "Vandeveer", 
                "Wiger", 
                "Wolf"
            ], 
            "negatives": [
                "Cohen", 
                "Eaton", 
                "Goodwin", 
                "Lourey", 
                "Marty", 
                "McGuire", 
                "Ortman", 
                "Reinert", 
                "Rest", 
                "Sheran", 
                "Sieben", 
                "Skoe", 
                "Tomassoni"
            ]
        }, 
        {
            "title": "H.F. No. 2506", 
            "pass": true, 
            "status_string": "passed and its title was agreed to", 
            "amended": false, 
            "yays": 56, 
            "nays": 6, 
            "affirmatives": [
                "Bakk", 
                "Benson", 
                "Bonoff", 
                "Brown", 
                "Carlson", 
                "Chamberlain", 
                "Cohen", 
                "Dahms", 
                "Daley", 
                "DeKruif", 
                "Dziedzic", 
                "Fischbach", 
                "Gazelka", 
                "Gerlach", 
                "Gimse", 
                "Goodwin", 
                "Hall", 
                "Hann", 
                "Harrington", 
                "Hayden", 
                "Higgins", 
                "Hoffman", 
                "Howe", 
                "Ingebrigtsen", 
                "Jungbauer", 
                "Kelash", 
                "Koch", 
                "Kruse", 
                "Latz", 
                "Lillie", 
                "Limmer", 
                "McGuire", 
                "Metzen", 
                "Miller", 
                "Nelson", 
                "Newman", 
                "Nienow", 
                "Olson", 
                "Ortman", 
                "Pappas", 
                "Parry", 
                "Pederson", 
                "Rest", 
                "Robling", 
                "Rosen", 
                "Saxhaug", 
                "Senjem", 
                "Sieben", 
                "Skoe", 
                "Sparks", 
                "Stumpf", 
                "Thompson", 
                "Torres Ray", 
                "Vandeveer", 
                "Wiger", 
                "Wolf"
            ], 
            "negatives": [
                "Eaton", 
                "Lourey", 
                "Marty", 
                "Reinert", 
                "Sheran", 
                "Tomassoni"
            ]
        }, 
        {
            "title": "S.F. No. 1804", 
            "pass": true, 
            "status_string": "passed and its title was agreed to", 
            "amended": false, 
            "yays": 59, 
            "nays": 0, 
            "affirmatives": [
                "Bakk", 
                "Benson", 
                "Bonoff", 
                "Brown", 
                "Carlson", 
                "Chamberlain", 
                "Cohen", 
                "Dahms", 
                "Daley", 
                "DeKruif", 
                "Dziedzic", 
                "Eaton", 
                "Fischbach", 
                "Gazelka", 
                "Gimse", 
                "Goodwin", 
                "Hall", 
                "Hann", 
                "Harrington", 
                "Hayden", 
                "Higgins", 
                "Hoffman", 
                "Howe", 
                "Jungbauer", 
                "Kelash", 
                "Koch", 
                "Kruse", 
                "Latz", 
                "Lillie", 
                "Limmer", 
                "Lourey", 
                "Marty", 
                "McGuire", 
                "Metzen", 
                "Miller", 
                "Nelson", 
                "Newman", 
                "Nienow", 
                "Olson", 
                "Ortman", 
                "Pappas", 
                "Pederson", 
                "Reinert", 
                "Rest", 
                "Robling", 
                "Rosen", 
                "Saxhaug", 
                "Senjem", 
                "Sheran", 
                "Sieben", 
                "Skoe", 
                "Sparks", 
                "Stumpf", 
                "Thompson", 
                "Tomassoni", 
                "Torres Ray", 
                "Vandeveer", 
                "Wiger", 
                "Wolf"
            ], 
            "negatives": []
        }, 
        {
            "title": "S.F. No. 2188", 
            "pass": true, 
            "status_string": "passed and its title was agreed to", 
            "amended": false, 
            "yays": 60, 
            "nays": 0, 
            "affirmatives": [
                "Bakk", 
                "Benson", 
                "Bonoff", 
                "Brown", 
                "Carlson", 
                "Chamberlain", 
                "Cohen", 
                "Dahms", 
                "Daley", 
                "DeKruif", 
                "Dziedzic", 
                "Eaton", 
                "Fischbach", 
                "Gazelka", 
                "Gerlach", 
                "Gimse", 
                "Goodwin", 
                "Hall", 
                "Hann", 
                "Harrington", 
                "Hayden", 
                "Higgins", 
                "Hoffman", 
                "Howe", 
                "Jungbauer", 
                "Kelash", 
                "Koch", 
                "Latz", 
                "Lillie", 
                "Limmer", 
                "Lourey", 
                "Marty", 
                "McGuire", 
                "Metzen", 
                "Miller", 
                "Nelson", 
                "Newman", 
                "Nienow", 
                "Olson", 
                "Ortman", 
                "Pappas", 
                "Parry", 
                "Pederson", 
                "Reinert", 
                "Rest", 
                "Robling", 
                "Rosen", 
                "Saxhaug", 
                "Senjem", 
                "Sheran", 
                "Sieben", 
                "Skoe", 
                "Sparks", 
                "Stumpf", 
                "Thompson", 
                "Tomassoni", 
                "Torres Ray", 
                "Vandeveer", 
                "Wiger", 
                "Wolf"
            ], 
            "negatives": []
        }, 
        {
            "title": "S.F. No. 2357", 
            "pass": true, 
            "status_string": "passed and its title was agreed to", 
            "amended": false, 
            "yays": 62, 
            "nays": 0, 
            "affirmatives": [
                "Bakk", 
                "Benson", 
                "Bonoff", 
                "Brown", 
                "Carlson", 
                "Chamberlain", 
                "Cohen", 
                "Dahms", 
                "Daley", 
                "DeKruif", 
                "Dziedzic", 
                "Eaton", 
                "Fischbach", 
                "Gazelka", 
                "Gerlach", 
                "Gimse", 
                "Goodwin", 
                "Hall", 
                "Hann", 
                "Harrington", 
                "Hayden", 
                "Higgins", 
                "Hoffman", 
                "Howe", 
                "Ingebrigtsen", 
                "Jungbauer", 
                "Kelash", 
                "Koch", 
                "Kruse", 
                "Latz", 
                "Lillie", 
                "Limmer", 
                "Lourey", 
                "Marty", 
                "McGuire", 
                "Metzen", 
                "Miller", 
                "Nelson", 
                "Newman", 
                "Nienow", 
                "Olson", 
                "Ortman", 
                "Pappas", 
                "Parry", 
                "Pederson", 
                "Reinert", 
                "Rest", 
                "Robling", 
                "Rosen", 
                "Saxhaug", 
                "Senjem", 
                "Sheran", 
                "Sieben", 
                "Skoe", 
                "Sparks", 
                "Stumpf", 
                "Thompson", 
                "Tomassoni", 
                "Torres Ray", 
                "Vandeveer", 
                "Wiger", 
                "Wolf"
            ], 
            "negatives": []
        }, 
        {
            "title": "S.F. No. 1679", 
            "pass": true, 
            "status_string": "passed and its title was agreed to", 
            "amended": false, 
            "yays": 49, 
            "nays": 13, 
            "affirmatives": [
                "Bakk", 
                "Bonoff", 
                "Carlson", 
                "Cohen", 
                "Dahms", 
                "Daley", 
                "Dziedzic", 
                "Eaton", 
                "Fischbach", 
                "Gerlach", 
                "Gimse", 
                "Goodwin", 
                "Hall", 
                "Hann", 
                "Harrington", 
                "Hayden", 
                "Higgins", 
                "Howe", 
                "Ingebrigtsen", 
                "Jungbauer", 
                "Kelash", 
                "Koch", 
                "Latz", 
                "Lourey", 
                "Marty", 
                "McGuire", 
                "Metzen", 
                "Miller", 
                "Nelson", 
                "Nienow", 
                "Olson", 
                "Ortman", 
                "Pappas", 
                "Parry", 
                "Pederson", 
                "Reinert", 
                "Rest", 
                "Robling", 
                "Rosen", 
                "Saxhaug", 
                "Senjem", 
                "Sheran", 
                "Sieben", 
                "Skoe", 
                "Sparks", 
                "Stumpf", 
                "Tomassoni", 
                "Torres Ray", 
                "Wiger"
            ], 
            "negatives": [
                "Benson", 
                "Brown", 
                "Chamberlain", 
                "DeKruif", 
                "Gazelka", 
                "Hoffman", 
                "Kruse", 
                "Lillie", 
                "Limmer", 
                "Newman", 
                "Thompson", 
                "Vandeveer", 
                "Wolf"
            ]
        }, 
        {
            "title": "H.F. No. 2294", 
            "pass": true, 
            "status_string": " amended, was passed and its title was agreed to", 
            "amended": false, 
            "yays": 45, 
            "nays": 16, 
            "affirmatives": [
                "Benson", 
                "Bonoff", 
                "Brown", 
                "Carlson", 
                "Chamberlain", 
                "Dahms", 
                "Daley", 
                "DeKruif", 
                "Fischbach", 
                "Gazelka", 
                "Gerlach", 
                "Gimse", 
                "Hall", 
                "Hann", 
                "Higgins", 
                "Hoffman", 
                "Howe", 
                "Ingebrigtsen", 
                "Jungbauer", 
                "Koch", 
                "Kruse", 
                "Lillie", 
                "Limmer", 
                "Lourey", 
                "Metzen", 
                "Miller", 
                "Nelson", 
                "Newman", 
                "Nienow", 
                "Olson", 
                "Ortman", 
                "Parry", 
                "Pederson", 
                "Reinert", 
                "Robling", 
                "Rosen", 
                "Saxhaug", 
                "Senjem", 
                "Skoe", 
                "Sparks", 
                "Stumpf", 
                "Thompson", 
                "Tomassoni", 
                "Vandeveer", 
                "Wolf"
            ], 
            "negatives": [
                "Bakk", 
                "Cohen", 
                "Dziedzic", 
                "Eaton", 
                "Goodwin", 
                "Harrington", 
                "Hayden", 
                "Kelash", 
                "Latz", 
                "Marty", 
                "McGuire", 
                "Pappas", 
                "Rest", 
                "Sieben", 
                "Torres Ray", 
                "Wiger"
            ]
        }
    ], 
    "filename": "2011_2012/sessions/txt/20120405101.txt"
}
