{
    "date": {
        "session_day": "43rd day", 
        "date_utc": "2009-04-28T00:00:00", 
        "date_string": "TUESDAY, APRIL 28, 2009"
    }, 
    "role_call": [
        "Anderson", 
        "Bakk", 
        "Berglin", 
        "Betzold", 
        "Carlson", 
        "Chaudhary", 
        "Clark", 
        "Cohen", 
        "Dahle", 
        "Day", 
        "Dibble", 
        "Dille", 
        "Doll", 
        "Erickson Ropes", 
        "Fischbach", 
        "Fobbe", 
        "Foley", 
        "Frederickson", 
        "Gerlach", 
        "Gimse", 
        "Hann", 
        "Higgins", 
        "Ingebrigtsen", 
        "Johnson", 
        "Jungbauer", 
        "Kelash", 
        "Koch", 
        "Koering", 
        "Kubly", 
        "Langseth", 
        "Latz", 
        "Limmer", 
        "Lourey", 
        "Lynch", 
        "Marty", 
        "Metzen", 
        "Michel", 
        "Moua", 
        "Murphy", 
        "Olseen", 
        "Olson, G.", 
        "Olson, M.", 
        "Ortman", 
        "Pappas", 
        "Pariseau", 
        "Pogemiller", 
        "Prettner Solon", 
        "Rest", 
        "Robling", 
        "Rosen", 
        "Rummel", 
        "Saltzman", 
        "Saxhaug", 
        "Scheid", 
        "Senjem", 
        "Sheran", 
        "Sieben", 
        "Skoe", 
        "Skogen", 
        "Sparks", 
        "Stumpf", 
        "Tomassoni", 
        "Torres Ray", 
        "Vandeveer", 
        "Vickerman", 
        "Wiger"
    ], 
    "votes": [
        {
            "affirmatives": [
                "Anderson", 
                "Anderson", 
                "Bakk", 
                "Bakk", 
                "Berglin", 
                "Berglin", 
                "Betzold", 
                "Betzold", 
                "CALL OF THE SENATE", 
                "Carlson", 
                "Carlson", 
                "Chaudhary", 
                "Chaudhary", 
                "Clark", 
                "Clark", 
                "Cohen", 
                "Cohen", 
                "Dahle", 
                "Dahle", 
                "Day", 
                "Day", 
                "Delete everything after the enacting clause, and delete the title, of H.F. No. 2323, and insert the", 
                "Dibble", 
                "Dibble", 
                "Dille", 
                "Dille", 
                "Doll", 
                "Doll", 
                "Erickson Ropes", 
                "Erickson Ropes", 
                "Fischbach", 
                "Fischbach", 
                "Fobbe", 
                "Fobbe", 
                "Foley", 
                "Foley", 
                "Frederickson", 
                "Frederickson", 
                "Gerlach", 
                "Gerlach", 
                "Gimse", 
                "Gimse", 
                "H.F. No. 2323 was read the second time.", 
                "H.F. No. 2323 was read the third time, as amended, and placed on its final passage.", 
                "Hann", 
                "Hann", 
                "Higgins", 
                "Higgins", 
                "Ingebrigtsen", 
                "Ingebrigtsen", 
                "Johnson", 
                "Johnson", 
                "Jungbauer", 
                "Jungbauer", 
                "Kelash", 
                "Kelash", 
                "Koch", 
                "Koch", 
                "Kubly", 
                "Kubly", 
                "Langseth", 
                "Langseth", 
                "Latz", 
                "Latz", 
                "Limmer", 
                "Limmer", 
                "Lourey", 
                "Lourey", 
                "Lynch", 
                "Lynch", 
                "Marty", 
                "Marty", 
                "Metzen", 
                "Metzen", 
                "Michel", 
                "Michel", 
                "Moua", 
                "Moua", 
                "Murphy", 
                "Murphy", 
                "Olseen", 
                "Olseen", 
                "Olson, G.", 
                "Olson, G.", 
                "Olson, M.", 
                "Olson, M.", 
                "Ortman", 
                "Ortman", 
                "Pappas", 
                "Pappas", 
                "Pariseau", 
                "Pariseau", 
                "Pogemiller", 
                "Pogemiller", 
                "Prettner Solon", 
                "Prettner Solon", 
                "Rest", 
                "Rest", 
                "Robling", 
                "Robling", 
                "Rosen", 
                "Rosen", 
                "Rummel", 
                "Rummel", 
                "Saltzman", 
                "Saltzman", 
                "Saxhaug", 
                "Saxhaug", 
                "Scheid", 
                "Scheid", 
                "Senator Bakk imposed a call of the Senate. The Sergeant at Arms was instructed to bring in the", 
                "Senator Bakk moved to amend H.F. No. 2323 as follows:", 
                "Senjem", 
                "Senjem", 
                "Sheran", 
                "Sheran", 
                "Sieben", 
                "Sieben", 
                "Skoe", 
                "Skoe", 
                "Skogen", 
                "Skogen", 
                "Sparks", 
                "Sparks", 
                "Stumpf", 
                "Stumpf", 
                "The motion prevailed.", 
                "The motion prevailed. So the amendment was adopted.", 
                "The question was taken on the passage of the bill, as amended.", 
                "The roll was called, and there were yeas 35 and nays 30, as follows:", 
                "Those who voted in the affirmative were:", 
                "Those who voted in the negative were:", 
                "Those who voted in the negative were:", 
                "Tomassoni", 
                "Tomassoni", 
                "Torres Ray", 
                "Torres Ray", 
                "Vandeveer", 
                "Vandeveer", 
                "Vickerman", 
                "Vickerman", 
                "Wiger", 
                "Wiger", 
                "absent members.", 
                "language after the enacting clause, and the title, of S.F. No. 2074, the second engrossment."
            ], 
            "negatives": [
                "Anderson", 
                "Bakk", 
                "Berglin", 
                "Betzold", 
                "CALL OF THE SENATE", 
                "Carlson", 
                "Chaudhary", 
                "Clark", 
                "Cohen", 
                "Dahle", 
                "Day", 
                "Day", 
                "Delete everything after the enacting clause, and delete the title, of H.F. No. 2323, and insert the", 
                "Dibble", 
                "Dille", 
                "Dille", 
                "Doll", 
                "Erickson Ropes", 
                "Fischbach", 
                "Fischbach", 
                "Fobbe", 
                "Foley", 
                "Frederickson", 
                "Gerlach", 
                "Gerlach", 
                "Gimse", 
                "Gimse", 
                "H.F. No. 2323 was read the second time.", 
                "H.F. No. 2323 was read the third time, as amended, and placed on its final passage.", 
                "Hann", 
                "Hann", 
                "Higgins", 
                "Ingebrigtsen", 
                "Ingebrigtsen", 
                "Johnson", 
                "Johnson", 
                "Jungbauer", 
                "Jungbauer", 
                "Kelash", 
                "Koch", 
                "Koch", 
                "Kubly", 
                "Langseth", 
                "Latz", 
                "Limmer", 
                "Limmer", 
                "Lourey", 
                "Lynch", 
                "Marty", 
                "Metzen", 
                "Michel", 
                "Michel", 
                "Moua", 
                "Murphy", 
                "Olseen", 
                "Olson, G.", 
                "Olson, M.", 
                "Ortman", 
                "Ortman", 
                "Pappas", 
                "Pariseau", 
                "Pogemiller", 
                "Prettner Solon", 
                "Rest", 
                "Robling", 
                "Robling", 
                "Rosen", 
                "Rosen", 
                "Rummel", 
                "Saltzman", 
                "Saxhaug", 
                "Scheid", 
                "Senator Bakk imposed a call of the Senate. The Sergeant at Arms was instructed to bring in the", 
                "Senator Bakk moved to amend H.F. No. 2323 as follows:", 
                "Senjem", 
                "Senjem", 
                "Sheran", 
                "Sieben", 
                "Skoe", 
                "Skogen", 
                "Sparks", 
                "Stumpf", 
                "The motion prevailed.", 
                "The motion prevailed. So the amendment was adopted.", 
                "The question was taken on the passage of the bill, as amended.", 
                "The roll was called, and there were yeas 35 and nays 30, as follows:", 
                "Those who voted in the affirmative were:", 
                "Those who voted in the negative were:", 
                "Tomassoni", 
                "Torres Ray", 
                "Vandeveer", 
                "Vandeveer", 
                "Vickerman", 
                "Wiger", 
                "absent members.", 
                "language after the enacting clause, and the title, of S.F. No. 2074, the second engrossment."
            ], 
            "title": "H.F. No. 2323"
        }, 
        {
            "affirmatives": [
                "Anderson", 
                "Bakk", 
                "Berglin", 
                "Betzold", 
                "Carlson", 
                "Chaudhary", 
                "Clark", 
                "Cohen", 
                "Dahle", 
                "Day", 
                "Dibble", 
                "Dille", 
                "Doll", 
                "Erickson Ropes", 
                "Fischbach", 
                "Fobbe", 
                "Foley", 
                "Frederickson", 
                "Gerlach", 
                "Gimse", 
                "Hann", 
                "Higgins", 
                "Ingebrigtsen", 
                "Johnson", 
                "Jungbauer", 
                "Kelash", 
                "Koch", 
                "Kubly", 
                "Langseth", 
                "Latz", 
                "Limmer", 
                "Lourey", 
                "Lynch", 
                "Marty", 
                "Metzen", 
                "Michel", 
                "Moua", 
                "Murphy", 
                "Olseen", 
                "Olson, G.", 
                "Olson, M.", 
                "Ortman", 
                "Pappas", 
                "Pariseau", 
                "Pogemiller", 
                "Prettner Solon", 
                "Rest", 
                "Robling", 
                "Rosen", 
                "Rummel", 
                "Saltzman", 
                "Saxhaug", 
                "Scheid", 
                "Senjem", 
                "Sheran", 
                "Sieben", 
                "Skoe", 
                "Skogen", 
                "Sparks", 
                "Stumpf", 
                "Those who voted in the negative were:", 
                "Tomassoni", 
                "Torres Ray", 
                "Vandeveer", 
                "Vickerman", 
                "Wiger"
            ], 
            "negatives": [
                "Day", 
                "Erickson Ropes", 
                "Fischbach", 
                "Frederickson", 
                "Gerlach", 
                "Gimse", 
                "Hann", 
                "Ingebrigtsen", 
                "Johnson", 
                "Jungbauer", 
                "Koch", 
                "Kubly", 
                "Limmer", 
                "Marty", 
                "Michel", 
                "Olson, G.", 
                "Olson, M.", 
                "Ortman", 
                "Pariseau", 
                "Robling", 
                "Senjem", 
                "Skogen", 
                "Sparks", 
                "Vandeveer", 
                "Vickerman"
            ], 
            "title": "H.F. No. 1362"
        }
    ], 
    "filename": "2009_2010/sessions/txt/20090428043.txt"
}
