{
    "date": {
        "session_day": "52nd day", 
        "date_iso": "2009-05-12T00:00:00", 
        "date_string": "TUESDAY, MAY 12, 2009"
    }, 
    "role_call": [
        "Anderson", 
        "Bakk", 
        "Berglin", 
        "Betzold", 
        "Bonoff", 
        "Carlson", 
        "Chaudhary", 
        "Clark", 
        "Cohen", 
        "Dahle", 
        "Day", 
        "Dibble", 
        "Dille", 
        "Doll", 
        "Erickson Ropes", 
        "Fischbach", 
        "Fobbe", 
        "Foley", 
        "Frederickson", 
        "Gerlach", 
        "Gimse", 
        "Hann", 
        "Higgins", 
        "Ingebrigtsen", 
        "Johnson", 
        "Jungbauer", 
        "Kelash", 
        "Koch", 
        "Koering", 
        "Kubly", 
        "Langseth", 
        "Latz", 
        "Limmer", 
        "Lourey", 
        "Lynch", 
        "Marty", 
        "Metzen", 
        "Michel", 
        "Moua", 
        "Murphy", 
        "Olseen", 
        "Olson, G.", 
        "Olson, M.", 
        "Ortman", 
        "Pappas", 
        "Pogemiller", 
        "Prettner Solon", 
        "Rest", 
        "Robling", 
        "Rosen", 
        "Rummel", 
        "Saltzman", 
        "Saxhaug", 
        "Scheid", 
        "Senjem", 
        "Sheran", 
        "Sieben", 
        "Skoe", 
        "Skogen", 
        "Sparks", 
        "Stumpf", 
        "Tomassoni", 
        "Torres Ray", 
        "Vandeveer", 
        "Vickerman", 
        "Wiger"
    ], 
    "bill_votes": [
        {
            "title": "S.F. No. 764", 
            "pass": true, 
            "status_string": " amended, was repassed and its title was agreed to", 
            "amended": false, 
            "yays": 49, 
            "nays": 0, 
            "affirmatives": [
                "Anderson", 
                "Betzold", 
                "Bonoff", 
                "Carlson", 
                "Chaudhary", 
                "Clark", 
                "Cohen", 
                "Dahle", 
                "Day", 
                "Erickson Ropes", 
                "Fischbach", 
                "Fobbe", 
                "Foley", 
                "Frederickson", 
                "Gimse", 
                "Hann", 
                "Higgins", 
                "Johnson", 
                "Jungbauer", 
                "Koering", 
                "Kubly", 
                "Langseth", 
                "Latz", 
                "Limmer", 
                "Lynch", 
                "Marty", 
                "Metzen", 
                "Moua", 
                "Murphy", 
                "Olseen", 
                "Olson, G.", 
                "Olson, M.", 
                "Ortman", 
                "Pogemiller", 
                "Rest", 
                "Robling", 
                "Rummel", 
                "Saltzman", 
                "Saxhaug", 
                "Scheid", 
                "Senjem", 
                "Sieben", 
                "Skoe", 
                "Skogen", 
                "Sparks", 
                "Tomassoni", 
                "Torres Ray", 
                "Vickerman", 
                "Wiger"
            ], 
            "negatives": []
        }, 
        {
            "title": "S.F. No. 1033", 
            "pass": true, 
            "status_string": " amended, was repassed and its title was agreed to", 
            "amended": false, 
            "yays": 47, 
            "nays": 5, 
            "affirmatives": [
                "Anderson", 
                "Bakk", 
                "Betzold", 
                "Bonoff", 
                "Carlson", 
                "Chaudhary", 
                "Clark", 
                "Cohen", 
                "Dahle", 
                "Day", 
                "Dibble", 
                "Erickson Ropes", 
                "Fischbach", 
                "Fobbe", 
                "Foley", 
                "Frederickson", 
                "Gimse", 
                "Higgins", 
                "Ingebrigtsen", 
                "Koering", 
                "Kubly", 
                "Langseth", 
                "Latz", 
                "Lynch", 
                "Marty", 
                "Metzen", 
                "Moua", 
                "Murphy", 
                "Olseen", 
                "Olson, G.", 
                "Olson, M.", 
                "Pogemiller", 
                "Rest", 
                "Robling", 
                "Rummel", 
                "Saltzman", 
                "Saxhaug", 
                "Scheid", 
                "Senjem", 
                "Sieben", 
                "Skoe", 
                "Skogen", 
                "Sparks", 
                "Tomassoni", 
                "Torres Ray", 
                "Vickerman", 
                "Wiger"
            ], 
            "negatives": [
                "Hann", 
                "Johnson", 
                "Jungbauer", 
                "Limmer", 
                "Ortman"
            ]
        }, 
        {
            "title": "S.F. No. 99", 
            "pass": true, 
            "status_string": " amended, was repassed and its title was agreed to", 
            "amended": false, 
            "yays": 39, 
            "nays": 13, 
            "affirmatives": [
                "Anderson", 
                "Bakk", 
                "Betzold", 
                "Bonoff", 
                "Carlson", 
                "Chaudhary", 
                "Clark", 
                "Cohen", 
                "Dahle", 
                "Dibble", 
                "Erickson Ropes", 
                "Foley", 
                "Frederickson", 
                "Higgins", 
                "Jungbauer", 
                "Kelash", 
                "Kubly", 
                "Langseth", 
                "Latz", 
                "Lynch", 
                "Marty", 
                "Metzen", 
                "Moua", 
                "Murphy", 
                "Olseen", 
                "Olson, M.", 
                "Pogemiller", 
                "Rest", 
                "Rummel", 
                "Saltzman", 
                "Saxhaug", 
                "Scheid", 
                "Sieben", 
                "Skoe", 
                "Skogen", 
                "Tomassoni", 
                "Torres Ray", 
                "Vickerman", 
                "Wiger"
            ], 
            "negatives": [
                "Day", 
                "Fischbach", 
                "Gimse", 
                "Hann", 
                "Ingebrigtsen", 
                "Johnson", 
                "Koering", 
                "Limmer", 
                "Olson, G.", 
                "Ortman", 
                "Robling", 
                "Senjem", 
                "Sparks"
            ]
        }, 
        {
            "title": "H.F. No. 1298", 
            "pass": true, 
            "status_string": " amended, was passed and its title was agreed to", 
            "amended": false, 
            "yays": 54, 
            "nays": 12, 
            "affirmatives": [
                "Bakk", 
                "Berglin", 
                "Betzold", 
                "Bonoff", 
                "Carlson", 
                "Chaudhary", 
                "Clark", 
                "Cohen", 
                "Dahle", 
                "Day", 
                "Dibble", 
                "Dille", 
                "Doll", 
                "Erickson Ropes", 
                "Fischbach", 
                "Fobbe", 
                "Foley", 
                "Frederickson", 
                "Gimse", 
                "Higgins", 
                "Ingebrigtsen", 
                "Johnson", 
                "Kelash", 
                "Kubly", 
                "Langseth", 
                "Latz", 
                "Lourey", 
                "Lynch", 
                "Marty", 
                "Metzen", 
                "Moua", 
                "Murphy", 
                "Olseen", 
                "Olson, G.", 
                "Olson, M.", 
                "Pogemiller", 
                "Prettner Solon", 
                "Rest", 
                "Rosen", 
                "Rummel", 
                "Saltzman", 
                "Saxhaug", 
                "Scheid", 
                "Senjem", 
                "Sheran", 
                "Sieben", 
                "Skoe", 
                "Skogen", 
                "Sparks", 
                "Stumpf", 
                "Tomassoni", 
                "Torres Ray", 
                "Vickerman", 
                "Wiger"
            ], 
            "negatives": [
                "Anderson", 
                "Gerlach", 
                "Hann", 
                "Jungbauer", 
                "Koch", 
                "Koering", 
                "Limmer", 
                "Michel", 
                "Ortman", 
                "Pappas", 
                "Robling", 
                "Vandeveer"
            ]
        }
    ], 
    "filename": "2009_2010/sessions/txt/20090512052.txt"
}
