{
    "date": {
        "session_day": "117th day", 
        "date_iso": "2008-05-16T00:00:00", 
        "date_string": "FRIDAY, MAY 16, 2008"
    }, 
    "role_call": [
        "Anderson", 
        "Bakk", 
        "Berglin", 
        "Betzold", 
        "Bonoff", 
        "Carlson", 
        "Chaudhary", 
        "Clark", 
        "Cohen", 
        "Dahle", 
        "Day", 
        "Dibble", 
        "Dille", 
        "Doll", 
        "Erickson Ropes", 
        "Fischbach", 
        "Foley", 
        "Frederickson", 
        "Gerlach", 
        "Gimse", 
        "Hann", 
        "Higgins", 
        "Ingebrigtsen", 
        "Johnson", 
        "Jungbauer", 
        "Koch", 
        "Koering", 
        "Kubly", 
        "Langseth", 
        "Larson", 
        "Latz", 
        "Limmer", 
        "Lourey", 
        "Lynch", 
        "Marty", 
        "Metzen", 
        "Michel", 
        "Moua", 
        "Murphy", 
        "Olseen", 
        "Olson, G.", 
        "Olson, M.", 
        "Ortman", 
        "Pappas", 
        "Pariseau", 
        "Pogemiller", 
        "Prettner Solon", 
        "Rest", 
        "Robling", 
        "Rosen", 
        "Rummel", 
        "Saltzman", 
        "Saxhaug", 
        "Scheid", 
        "Senjem", 
        "Sheran", 
        "Sieben", 
        "Skoe", 
        "Skogen", 
        "Sparks", 
        "Stumpf", 
        "Tomassoni", 
        "Torres Ray", 
        "Vandeveer", 
        "Vickerman", 
        "Wergin", 
        "Wiger"
    ], 
    "bill_votes": [
        {
            "title": "S.F. No. 3594", 
            "pass": true, 
            "status_string": " amended, was repassed and its title was agreed to", 
            "amended": false, 
            "yays": 58, 
            "nays": 0, 
            "affirmatives": [
                "Bakk", 
                "Betzold", 
                "Bonoff", 
                "Carlson", 
                "Clark", 
                "Dahle", 
                "Day", 
                "Dibble", 
                "Dille", 
                "Doll", 
                "Fischbach", 
                "Foley", 
                "Frederickson", 
                "Gerlach", 
                "Gimse", 
                "Hann", 
                "Higgins", 
                "Ingebrigtsen", 
                "Johnson", 
                "Jungbauer", 
                "Koch", 
                "Kubly", 
                "Langseth", 
                "Larson", 
                "Latz", 
                "Limmer", 
                "Lourey", 
                "Lynch", 
                "Marty", 
                "Metzen", 
                "Michel", 
                "Moua", 
                "Murphy", 
                "Olseen", 
                "Olson, G.", 
                "Olson, M.", 
                "Ortman", 
                "Pappas", 
                "Pogemiller", 
                "Prettner Solon", 
                "Robling", 
                "Rosen", 
                "Rummel", 
                "Saltzman", 
                "Saxhaug", 
                "Scheid", 
                "Senjem", 
                "Sheran", 
                "Sieben", 
                "Skoe", 
                "Sparks", 
                "Stumpf", 
                "Tomassoni", 
                "Torres Ray", 
                "Vandeveer", 
                "Vickerman", 
                "Wergin", 
                "Wiger"
            ], 
            "negatives": []
        }, 
        {
            "title": "S.F. No. 3871", 
            "pass": true, 
            "status_string": " amended, was passed and its title was agreed to", 
            "amended": false, 
            "yays": 59, 
            "nays": 0, 
            "affirmatives": [
                "Anderson", 
                "Bakk", 
                "Berglin", 
                "Betzold", 
                "Bonoff", 
                "Carlson", 
                "Chaudhary", 
                "Clark", 
                "Cohen", 
                "Dahle", 
                "Day", 
                "Dibble", 
                "Dille", 
                "Doll", 
                "Fischbach", 
                "Foley", 
                "Frederickson", 
                "Gerlach", 
                "Gimse", 
                "Hann", 
                "Higgins", 
                "Ingebrigtsen", 
                "Johnson", 
                "Jungbauer", 
                "Koch", 
                "Kubly", 
                "Langseth", 
                "Larson", 
                "Latz", 
                "Limmer", 
                "Lourey", 
                "Lynch", 
                "Marty", 
                "Metzen", 
                "Michel", 
                "Murphy", 
                "Olseen", 
                "Olson, G.", 
                "Olson, M.", 
                "Ortman", 
                "Pappas", 
                "Pogemiller", 
                "Prettner Solon", 
                "Rest", 
                "Robling", 
                "Rosen", 
                "Rummel", 
                "Saltzman", 
                "Saxhaug", 
                "Scheid", 
                "Sheran", 
                "Sieben", 
                "Sparks", 
                "Stumpf", 
                "Tomassoni", 
                "Torres Ray", 
                "Vandeveer", 
                "Vickerman", 
                "Wiger"
            ], 
            "negatives": []
        }, 
        {
            "title": "S.F. No. 3535", 
            "pass": true, 
            "status_string": " amended, was passed and its title was agreed to", 
            "amended": false, 
            "yays": 59, 
            "nays": 5, 
            "affirmatives": [
                "Anderson", 
                "Bakk", 
                "Berglin", 
                "Betzold", 
                "Bonoff", 
                "Carlson", 
                "Chaudhary", 
                "Clark", 
                "Cohen", 
                "Dahle", 
                "Day", 
                "Dibble", 
                "Dille", 
                "Doll", 
                "Fischbach", 
                "Foley", 
                "Frederickson", 
                "Gerlach", 
                "Gimse", 
                "Hann", 
                "Higgins", 
                "Ingebrigtsen", 
                "Johnson", 
                "Jungbauer", 
                "Koch", 
                "Kubly", 
                "Langseth", 
                "Larson", 
                "Latz", 
                "Lourey", 
                "Lynch", 
                "Marty", 
                "Metzen", 
                "Michel", 
                "Moua", 
                "Murphy", 
                "Olseen", 
                "Olson, G.", 
                "Olson, M.", 
                "Pappas", 
                "Pogemiller", 
                "Prettner Solon", 
                "Rest", 
                "Robling", 
                "Rosen", 
                "Rummel", 
                "Saltzman", 
                "Saxhaug", 
                "Scheid", 
                "Sheran", 
                "Sieben", 
                "Skoe", 
                "Skogen", 
                "Sparks", 
                "Stumpf", 
                "Tomassoni", 
                "Torres Ray", 
                "Vickerman", 
                "Wiger"
            ], 
            "negatives": [
                "Limmer", 
                "Ortman", 
                "Pariseau", 
                "Senjem", 
                "Vandeveer"
            ]
        }, 
        {
            "title": "H.F. No. 1724", 
            "pass": true, 
            "status_string": " amended, was passed and its title was agreed to", 
            "amended": false, 
            "yays": 60, 
            "nays": 3, 
            "affirmatives": [
                "Anderson", 
                "Berglin", 
                "Betzold", 
                "Bonoff", 
                "Carlson", 
                "Clark", 
                "Cohen", 
                "Dahle", 
                "Day", 
                "Dibble", 
                "Dille", 
                "Doll", 
                "Fischbach", 
                "Foley", 
                "Frederickson", 
                "Gimse", 
                "Hann", 
                "Higgins", 
                "Ingebrigtsen", 
                "Johnson", 
                "Jungbauer", 
                "Koch", 
                "Kubly", 
                "Langseth", 
                "Larson", 
                "Latz", 
                "Limmer", 
                "Lourey", 
                "Lynch", 
                "Marty", 
                "Metzen", 
                "Michel", 
                "Moua", 
                "Murphy", 
                "Olseen", 
                "Olson, M.", 
                "Ortman", 
                "Pappas", 
                "Pariseau", 
                "Pogemiller", 
                "Prettner Solon", 
                "Rest", 
                "Robling", 
                "Rosen", 
                "Rummel", 
                "Saltzman", 
                "Saxhaug", 
                "Scheid", 
                "Senjem", 
                "Sheran", 
                "Sieben", 
                "Skoe", 
                "Skogen", 
                "Sparks", 
                "Stumpf", 
                "Tomassoni", 
                "Torres Ray", 
                "Vickerman", 
                "Wergin", 
                "Wiger"
            ], 
            "negatives": [
                "Gerlach", 
                "Olson, G.", 
                "Vandeveer"
            ]
        }, 
        {
            "title": "H.F. No. 3082", 
            "pass": true, 
            "status_string": " amended by the Conference Committee, was repassed and its title was agreed to", 
            "amended": false, 
            "yays": 57, 
            "nays": 8, 
            "affirmatives": [
                "Anderson", 
                "Bakk", 
                "Betzold", 
                "Bonoff", 
                "Carlson", 
                "Clark", 
                "Cohen", 
                "Dahle", 
                "Day", 
                "Dibble", 
                "Dille", 
                "Doll", 
                "Fischbach", 
                "Foley", 
                "Frederickson", 
                "Gimse", 
                "Hann", 
                "Higgins", 
                "Ingebrigtsen", 
                "Johnson", 
                "Koch", 
                "Koering", 
                "Kubly", 
                "Langseth", 
                "Larson", 
                "Latz", 
                "Limmer", 
                "Lourey", 
                "Lynch", 
                "Marty", 
                "Metzen", 
                "Michel", 
                "Moua", 
                "Murphy", 
                "Olseen", 
                "Olson, G.", 
                "Olson, M.", 
                "Pappas", 
                "Pariseau", 
                "Pogemiller", 
                "Prettner Solon", 
                "Rest", 
                "Robling", 
                "Rosen", 
                "Rummel", 
                "Saltzman", 
                "Saxhaug", 
                "Scheid", 
                "Senjem", 
                "Sieben", 
                "Skoe", 
                "Skogen", 
                "Sparks", 
                "Stumpf", 
                "Torres Ray", 
                "Vickerman", 
                "Wergin"
            ], 
            "negatives": [
                "Chaudhary", 
                "Erickson Ropes", 
                "Gerlach", 
                "Jungbauer", 
                "Sheran", 
                "Tomassoni", 
                "Vandeveer", 
                "Wiger"
            ]
        }, 
        {
            "title": "H.F. No. 3800", 
            "pass": true, 
            "status_string": " amended by the Conference Committee, was repassed and its title was agreed to", 
            "amended": false, 
            "yays": 62, 
            "nays": 5, 
            "affirmatives": [
                "Anderson", 
                "Bakk", 
                "Berglin", 
                "Betzold", 
                "Bonoff", 
                "Carlson", 
                "Chaudhary", 
                "Clark", 
                "Cohen", 
                "Dahle", 
                "Day", 
                "Dibble", 
                "Dille", 
                "Doll", 
                "Erickson Ropes", 
                "Fischbach", 
                "Foley", 
                "Frederickson", 
                "Gerlach", 
                "Gimse", 
                "Hann", 
                "Higgins", 
                "Ingebrigtsen", 
                "Johnson", 
                "Jungbauer", 
                "Koch", 
                "Koering", 
                "Kubly", 
                "Langseth", 
                "Larson", 
                "Latz", 
                "Limmer", 
                "Lourey", 
                "Lynch", 
                "Marty", 
                "Metzen", 
                "Michel", 
                "Moua", 
                "Murphy", 
                "Olseen", 
                "Olson, G.", 
                "Olson, M.", 
                "Ortman", 
                "Pappas", 
                "Pariseau", 
                "Pogemiller", 
                "Prettner Solon", 
                "Rest", 
                "Robling", 
                "Rosen", 
                "Rummel", 
                "Saltzman", 
                "Saxhaug", 
                "Scheid", 
                "Sheran", 
                "Sieben", 
                "Skoe", 
                "Skogen", 
                "Stumpf", 
                "Torres Ray", 
                "Vickerman", 
                "Wiger"
            ], 
            "negatives": [
                "Senjem", 
                "Sparks", 
                "Tomassoni", 
                "Vandeveer", 
                "Wergin"
            ]
        }, 
        {
            "title": "S.F. No. 100", 
            "pass": true, 
            "status_string": " amended, was repassed and its title was agreed to", 
            "amended": false, 
            "yays": 40, 
            "nays": 27, 
            "affirmatives": [
                "Anderson", 
                "Bakk", 
                "Berglin", 
                "Betzold", 
                "Bonoff", 
                "Carlson", 
                "Chaudhary", 
                "Clark", 
                "Cohen", 
                "Dahle", 
                "Dibble", 
                "Doll", 
                "Erickson Ropes", 
                "Foley", 
                "Higgins", 
                "Langseth", 
                "Larson", 
                "Latz", 
                "Lourey", 
                "Lynch", 
                "Marty", 
                "Metzen", 
                "Michel", 
                "Moua", 
                "Murphy", 
                "Olseen", 
                "Pappas", 
                "Pogemiller", 
                "Prettner Solon", 
                "Rest", 
                "Rummel", 
                "Saltzman", 
                "Saxhaug", 
                "Scheid", 
                "Sheran", 
                "Sieben", 
                "Skoe", 
                "Tomassoni", 
                "Torres Ray", 
                "Wiger"
            ], 
            "negatives": [
                "Day", 
                "Dille", 
                "Fischbach", 
                "Frederickson", 
                "Gerlach", 
                "Gimse", 
                "Hann", 
                "Ingebrigtsen", 
                "Johnson", 
                "Jungbauer", 
                "Koch", 
                "Koering", 
                "Kubly", 
                "Limmer", 
                "Olson, G.", 
                "Olson, M.", 
                "Ortman", 
                "Pariseau", 
                "Robling", 
                "Rosen", 
                "Senjem", 
                "Skogen", 
                "Sparks", 
                "Stumpf", 
                "Vandeveer", 
                "Vickerman", 
                "Wergin"
            ]
        }, 
        {
            "title": "S.F. No. 3360", 
            "pass": true, 
            "status_string": " amended by the Conference Committee, was repassed and its title was agreed to", 
            "amended": false, 
            "yays": 64, 
            "nays": 1, 
            "affirmatives": [
                "Anderson", 
                "Bakk", 
                "Berglin", 
                "Betzold", 
                "Bonoff", 
                "Carlson", 
                "Chaudhary", 
                "Clark", 
                "Cohen", 
                "Dahle", 
                "Day", 
                "Dibble", 
                "Dille", 
                "Doll", 
                "Erickson Ropes", 
                "Fischbach", 
                "Foley", 
                "Frederickson", 
                "Gerlach", 
                "Gimse", 
                "Hann", 
                "Higgins", 
                "Ingebrigtsen", 
                "Johnson", 
                "Jungbauer", 
                "Koch", 
                "Koering", 
                "Kubly", 
                "Langseth", 
                "Larson", 
                "Latz", 
                "Limmer", 
                "Lourey", 
                "Lynch", 
                "Marty", 
                "Metzen", 
                "Michel", 
                "Moua", 
                "Murphy", 
                "Olseen", 
                "Olson, G.", 
                "Olson, M.", 
                "Ortman", 
                "Pappas", 
                "Pariseau", 
                "Pogemiller", 
                "Prettner Solon", 
                "Rest", 
                "Robling", 
                "Rosen", 
                "Rummel", 
                "Saltzman", 
                "Saxhaug", 
                "Scheid", 
                "Sheran", 
                "Sieben", 
                "Skoe", 
                "Skogen", 
                "Sparks", 
                "Stumpf", 
                "Tomassoni", 
                "Torres Ray", 
                "Vickerman", 
                "Wiger"
            ], 
            "negatives": [
                "Vandeveer"
            ]
        }
    ], 
    "filename": "2008_2009/sessions/txt/20080516117.txt"
}
